ltctplugin/terminal/__init__.py
ltctplugin/terminal/gui.py
ltctplugin/terminal/terminal.wxui
ltctplugin/terminal/terminal.xrc
ltctplugin/terminal/work.py
ltchiptool_terminal-1.4.0.dist-info/METADATA
ltchiptool_terminal-1.4.0.dist-info/WHEEL
ltchiptool_terminal-1.4.0.dist-info/RECORD
